pypathutil/__init__.py
pypathutil/common.py
pypathutil/configs.py
pypathutil/main.py
pypathutil/static.py
pypathutil-0.0.17.dist-info/LICENSE
pypathutil-0.0.17.dist-info/METADATA
pypathutil-0.0.17.dist-info/WHEEL
pypathutil-0.0.17.dist-info/entry_points.txt
pypathutil-0.0.17.dist-info/top_level.txt
pypathutil-0.0.17.dist-info/RECORD
