Metadata-Version: 2.1
Name: pypathutil
Version: 0.0.17
Summary: command line utilities to help you work with paths
Home-page: https://veltzer.github.io/pypathutil
Download-URL: https://github.com/veltzer/pypathutil
Author: Mark Veltzer
Author-email: mark.veltzer@gmail.com
Maintainer: Mark Veltzer
Maintainer-email: mark.veltzer@gmail.com
License: MIT
Keywords: path,command-line,shell,reduce,append,remove
Platform: python3
Classifier: Development Status :: 4 - Beta
Classifier: Environment :: Console
Classifier: Operating System :: OS Independent
Classifier: Programming Language :: Python
Classifier: Programming Language :: Python :: 3
Classifier: Programming Language :: Python :: 3 :: Only
Classifier: Programming Language :: Python :: 3.11
Classifier: Topic :: Utilities
Classifier: License :: OSI Approved :: MIT License
License-File: LICENSE
Requires-Dist: pylogconf
Requires-Dist: pytconf
